Workbook
Name Date: Dashboard!$S$3
Name Date_Range: OFFSET(Dashboard!$AF$4,0,0,MATCH(TODAY(),Dashboard!$AF$4:$AF$337,0)+1)
Name Flow_Range: OFFSET(Dashboard!$AG$4,0,0,MATCH(TODAY(),Dashboard!$AF$4:$AF$337,0)+1)

Sheet Accounts Tasks
A3: RC | C3: Accounts' Status
C4: Account | E4: Lead | G4: Status
C5: Globe | E5: Yaniv | G5: STOP (only up to 2 hrs work can be completed) Data Modelling required for Misaligned Component - MRF flow
C6: Sprint | E6: Yaniv | G6: STOP (only up to 2 hrs work can be completed)
C7: XLCom | E7: Maya | G7: STOP (only up to 2 hrs work can be completed) Wrong Charging, Quota Not Update - waiting for UTS-Krrish resolve, Unsync - needs remodeling per new format
C8: Cricket | E8: Yaniv | G8: STOP (only up to 2 hrs work can be completed)
C9: USCC | E9: Yaniv | G9: STOP (only up to 2 hrs work can be completed) Uploaded 2 dispatch flows
C10: TefArg | E10: Maya | G10: STOP (only up to 2 hrs work can be completed) Pending full classification by Rodrigo + Decision which flows to model - Ongoing
C11: Bell Canada | E11: Maya | G11: STOP (only up to 2 hrs work can be completed) "User ID / Password Issue" flow modelled - Waiting for Krrish and AO configurations on site
A12: 0.3 monthly | C12: Airtel | E12: Maya | G12: High priority Deployed "Order Not Generated", Attachment config. For "Order Not Generated", Parsing - new atom for "NMS Release Scenario"
C13: Metro PCS | E13: Maya | G13: STOP (only up to 2 hrs work can be completed)
A14: 0.25 one time | C14: TKS | E14: Maya | G14: To start
C16: Open Tasks - Non Dev | E16: FP | G16: Note
C17: Maya KT | E17: Yaniv, Maya | G17: Started going through the Amily web service code
C18: DevOps in Amily | E18: Yaniv | G18: On hold
C19: UTS querying service | E19: Yaniv | G19: A story was opened in Jira by Galit
C20: Cluster validation using partially labeld data applied on documents | E20: Yaniv, Maya
C21: Limitation to number of values parsed - Ask Bharati/Hetal

Sheet Dashboard
D2: =SUM(D5:D50) -> 38 | E2: =SUM(E5:E50) -> 1 | F2: =SUM(F5:F50) -> 2 | G2: =SUM(G5:G50) -> 14 | H2: =SUM(H5:H50) -> 6 | I2: =SUM(I5:I50) -> 6 | K2: =SUM(K5:K50) -> 8 | L2: =SUM(L5:L50) -> 0 | M2: =SUM(M5:M50) -> 0 | N2: =SUM(N5:N50) -> 0 | O2: =SUM(O5:O50) -> 6
D3: E2E Automation Flows | K3: Dispatch Flows | AF3: Date | AG3: Flows
C4: Account Status | D4: Prod. - Activated | E4: Prod. - Deactivated | F4: Labeling | G4: Dev. | H4: Dev. - Testing | I4: Descoped | K4: Prod. - Activated | L4: Prod. - Deactivated | M4: Dev. | N4: Dev. - Testing | O4: Descoped | AF4: 42948 | AG4: =COUNTIF(Workflows!$U$4:$U$4024,"<="&AF4) -> 0
C5: Globe | D5: =COUNTIFS(Workflows!$B$4:$B$519,$C5,Workflows!$D$4:$D$519,D$4) -> 7 | E5: =COUNTIFS(Workflows!$B$4:$B$519,$C5,Workflows!$D$4:$D$519,E$4) -> 0 | F5: =COUNTIFS(Workflows!$B$4:$B$519,$C5,Workflows!$D$4:$D$519,F$4) -> 0 | G5: =COUNTIFS(Workflows!$B$4:$B$519,$C5,Workflows!$D$4:$D$519,G$4) -> 1 | H5: =COUNTIFS(Workflows!$B$4:$B$519,$C5,Workflows!$D$4:$D$519,H$4) -> 1 | I5: =COUNTIFS(Workflows!$B$4:$B$519,$C5,Workflows!$D$4:$D$519,I$4) -> 0 | K5: =COUNTIFS('Dispatch flows'!$B$4:$B$74,$C5,'Dispatch flows'!$D$4:$D$74,K$4) -> 3 | L5: =COUNTIFS('Dispatch flows'!$B$4:$B$74,$C5,'Dispatch flows'!$D$4:$D$74,L$4) -> 0 | M5: =COUNTIFS('Dispatch flows'!$B$4:$B$74,$C5,'Dispatch flows'!$D$4:$D$74,M$4) -> 0 | N5: =COUNTIFS('Dispatch flows'!$B$4:$B$74,$C5,'Dispatch flows'!$D$4:$D$74,N$4) -> 0 | O5: =COUNTIFS('Dispatch flows'!$B$4:$B$74,$C5,'Dispatch flows'!$D$4:$D$74,O$4) -> 3 | AF5: 42949 | AG5: =COUNTIF(Workflows!$U$4:$U$4024,"<="&AF5) -> 0
C6: Sprint | D6: =COUNTIFS(Workflows!$B$4:$B$519,$C6,Workflows!$D$4:$D$519,D$4) -> 11 | E6: =COUNTIFS(Workflows!$B$4:$B$519,$C6,Workflows!$D$4:$D$519,E$4) -> 0 | F6: =COUNTIFS(Workflows!$B$4:$B$519,$C6,Workflows!$D$4:$D$519,F$4) -> 0 | G6: =COUNTIFS(Workflows!$B$4:$B$519,$C6,Workflows!$D$4:$D$519,G$4) -> 0 | H6: =COUNTIFS(Workflows!$B$4:$B$519,$C6,Workflows!$D$4:$D$519,H$4) -> 0 | I6: =COUNTIFS(Workflows!$B$4:$B$519,$C6,Workflows!$D$4:$D$519,I$4) -> 0 | K6: =COUNTIFS('Dispatch flows'!$B$4:$B$74,$C6,'Dispatch flows'!$D$4:$D$74,K$4) -> 3 | L6: =COUNTIFS('Dispatch flows'!$B$4:$B$74,$C6,'Dispatch flows'!$D$4:$D$74,L$4) -> 0 | M6: =COUNTIFS('Dispatch flows'!$B$4:$B$74,$C6,'Dispatch flows'!$D$4:$D$74,M$4) -> 0 | N6: =COUNTIFS('Dispatch flows'!$B$4:$B$74,$C6,'Dispatch flows'!$D$4:$D$74,N$4) -> 0 | O6: =COUNTIFS('Dispatch flows'!$B$4:$B$74,$C6,'Dispatch flows'!$D$4:$D$74,O$4) -> 0 | AF6: 42950 | AG6: =COUNTIF(Workflows!$U$4:$U$4024,"<="&AF6) -> 0
C7: XL Axiata | D7: =COUNTIFS(Workflows!$B$4:$B$519,$C7,Workflows!$D$4:$D$519,D$4) -> 4 | E7: =COUNTIFS(Workflows!$B$4:$B$519,$C7,Workflows!$D$4:$D$519,E$4) -> 1 | F7: =COUNTIFS(Workflows!$B$4:$B$519,$C7,Workflows!$D$4:$D$519,F$4) -> 1 | G7: =COUNTIFS(Workflows!$B$4:$B$519,$C7,Workflows!$D$4:$D$519,G$4) -> 0 | H7: =COUNTIFS(Workflows!$B$4:$B$519,$C7,Workflows!$D$4:$D$519,H$4) -> 1 | I7: =COUNTIFS(Workflows!$B$4:$B$519,$C7,Workflows!$D$4:$D$519,I$4) -> 0 | K7: =COUNTIFS('Dispatch flows'!$B$4:$B$74,$C7,'Dispatch flows'!$D$4:$D$74,K$4) -> 0 | L7: =COUNTIFS('Dispatch flows'!$B$4:$B$74,$C7,'Dispatch flows'!$D$4:$D$74,L$4) -> 0 | M7: =COUNTIFS('Dispatch flows'!$B$4:$B$74,$C7,'Dispatch flows'!$D$4:$D$74,M$4) -> 0 | N7: =COUNTIFS('Dispatch flows'!$B$4:$B$74,$C7,'Dispatch flows'!$D$4:$D$74,N$4) -> 0 | O7: =COUNTIFS('Dispatch flows'!$B$4:$B$74,$C7,'Dispatch flows'!$D$4:$D$74,O$4) -> 0 | AF7: 42951 | AG7: =COUNTIF(Workflows!$U$4:$U$4024,"<="&AF7) -> 0
C8: Cricket | D8: =COUNTIFS(Workflows!$B$4:$B$519,$C8,Workflows!$D$4:$D$519,D$4) -> 7 | E8: =COUNTIFS(Workflows!$B$4:$B$519,$C8,Workflows!$D$4:$D$519,E$4) -> 0 | F8: =COUNTIFS(Workflows!$B$4:$B$519,$C8,Workflows!$D$4:$D$519,F$4) -> 0 | G8: =COUNTIFS(Workflows!$B$4:$B$519,$C8,Workflows!$D$4:$D$519,G$4) -> 0 | H8: =COUNTIFS(Workflows!$B$4:$B$519,$C8,Workflows!$D$4:$D$519,H$4) -> 1 | I8: =COUNTIFS(Workflows!$B$4:$B$519,$C8,Workflows!$D$4:$D$519,I$4) -> 6 | K8: =COUNTIFS('Dispatch flows'!$B$4:$B$74,$C8,'Dispatch flows'!$D$4:$D$74,K$4) -> 0 | L8: =COUNTIFS('Dispatch flows'!$B$4:$B$74,$C8,'Dispatch flows'!$D$4:$D$74,L$4) -> 0 | M8: =COUNTIFS('Dispatch flows'!$B$4:$B$74,$C8,'Dispatch flows'!$D$4:$D$74,M$4) -> 0 | N8: =COUNTIFS('Dispatch flows'!$B$4:$B$74,$C8,'Dispatch flows'!$D$4:$D$74,N$4) -> 0 | O8: =COUNTIFS('Dispatch flows'!$B$4:$B$74,$C8,'Dispatch flows'!$D$4:$D$74,O$4) -> 0 | AF8: 42952 | AG8: =COUNTIF(Workflows!$U$4:$U$4024,"<="&AF8) -> 0
C9: USCC | D9: =COUNTIFS(Workflows!$B$4:$B$519,$C9,Workflows!$D$4:$D$519,D$4) -> 4 | E9: =COUNTIFS(Workflows!$B$4:$B$519,$C9,Workflows!$D$4:$D$519,E$4) -> 0 | F9: =COUNTIFS(Workflows!$B$4:$B$519,$C9,Workflows!$D$4:$D$519,F$4) -> 0 | G9: =COUNTIFS(Workflows!$B$4:$B$519,$C9,Workflows!$D$4:$D$519,G$4) -> 2 | H9: =COUNTIFS(Workflows!$B$4:$B$519,$C9,Workflows!$D$4:$D$519,H$4) -> 2 | I9: =COUNTIFS(Workflows!$B$4:$B$519,$C9,Workflows!$D$4:$D$519,I$4) -> 0 | K9: =COUNTIFS('Dispatch flows'!$B$4:$B$74,$C9,'Dispatch flows'!$D$4:$D$74,K$4) -> 2 | L9: =COUNTIFS('Dispatch flows'!$B$4:$B$74,$C9,'Dispatch flows'!$D$4:$D$74,L$4) -> 0 | M9: =COUNTIFS('Dispatch flows'!$B$4:$B$74,$C9,'Dispatch flows'!$D$4:$D$74,M$4) -> 0 | N9: =COUNTIFS('Dispatch flows'!$B$4:$B$74,$C9,'Dispatch flows'!$D$4:$D$74,N$4) -> 0 | O9: =COUNTIFS('Dispatch flows'!$B$4:$B$74,$C9,'Dispatch flows'!$D$4:$D$74,O$4) -> 3 | AF9: 42953 | AG9: =COUNTIF(Workflows!$U$4:$U$4024,"<="&AF9) -> 8
C10: Bell Canada | D10: =COUNTIFS(Workflows!$B$4:$B$519,$C10,Workflows!$D$4:$D$519,D$4) -> 0 | E10: =COUNTIFS(Workflows!$B$4:$B$519,$C10,Workflows!$D$4:$D$519,E$4) -> 0 | F10: =COUNTIFS(Workflows!$B$4:$B$519,$C10,Workflows!$D$4:$D$519,F$4) -> 0 | G10: =COUNTIFS(Workflows!$B$4:$B$519,$C10,Workflows!$D$4:$D$519,G$4) -> 3 | H10: =COUNTIFS(Workflows!$B$4:$B$519,$C10,Workflows!$D$4:$D$519,H$4) -> 0 | I10: =COUNTIFS(Workflows!$B$4:$B$519,$C10,Workflows!$D$4:$D$519,I$4) -> 0 | K10: =COUNTIFS('Dispatch flows'!$B$4:$B$74,$C10,'Dispatch flows'!$D$4:$D$74,K$4) -> 0 | L10: =COUNTIFS('Dispatch flows'!$B$4:$B$74,$C10,'Dispatch flows'!$D$4:$D$74,L$4) -> 0 | M10: =COUNTIFS('Dispatch flows'!$B$4:$B$74,$C10,'Dispatch flows'!$D$4:$D$74,M$4) -> 0 | N10: =COUNTIFS('Dispatch flows'!$B$4:$B$74,$C10,'Dispatch flows'!$D$4:$D$74,N$4) -> 0 | O10: =COUNTIFS('Dispatch flows'!$B$4:$B$74,$C10,'Dispatch flows'!$D$4:$D$74,O$4) -> 0 | AF10: 42954 | AG10: =COUNTIF(Workflows!$U$4:$U$4024,"<="&AF10) -> 8
C11: Airtel | D11: =COUNTIFS(Workflows!$B$4:$B$519,$C11,Workflows!$D$4:$D$519,D$4) -> 5 | E11: =COUNTIFS(Workflows!$B$4:$B$519,$C11,Workflows!$D$4:$D$519,E$4) -> 0 | F11: =COUNTIFS(Workflows!$B$4:$B$519,$C11,Workflows!$D$4:$D$519,F$4) -> 0 | G11: =COUNTIFS(Workflows!$B$4:$B$519,$C11,Workflows!$D$4:$D$519,G$4) -> 3 | H11: =COUNTIFS(Workflows!$B$4:$B$519,$C11,Workflows!$D$4:$D$519,H$4) -> 1 | I11: =COUNTIFS(Workflows!$B$4:$B$519,$C11,Workflows!$D$4:$D$519,I$4) -> 0 | K11: =COUNTIFS('Dispatch flows'!$B$4:$B$74,$C11,'Dispatch flows'!$D$4:$D$74,K$4) -> 0 | L11: =COUNTIFS('Dispatch flows'!$B$4:$B$74,$C11,'Dispatch flows'!$D$4:$D$74,L$4) -> 0 | M11: =COUNTIFS('Dispatch flows'!$B$4:$B$74,$C11,'Dispatch flows'!$D$4:$D$74,M$4) -> 0 | N11: =COUNTIFS('Dispatch flows'!$B$4:$B$74,$C11,'Dispatch flows'!$D$4:$D$74,N$4) -> 0 | O11: =COUNTIFS('Dispatch flows'!$B$4:$B$74,$C11,'Dispatch flows'!$D$4:$D$74,O$4) -> 0 | AF11: 42955 | AG11: =COUNTIF(Workflows!$U$4:$U$4024,"<="&AF11) -> 8
C12: Tef Argentina | D12: =COUNTIFS(Workflows!$B$4:$B$519,$C12,Workflows!$D$4:$D$519,D$4) -> 0 | E12: =COUNTIFS(Workflows!$B$4:$B$519,$C12,Workflows!$D$4:$D$519,E$4) -> 0 | F12: =COUNTIFS(Workflows!$B$4:$B$519,$C12,Workflows!$D$4:$D$519,F$4) -> 0 | G12: =COUNTIFS(Workflows!$B$4:$B$519,$C12,Workflows!$D$4:$D$519,G$4) -> 1 | H12: =COUNTIFS(Workflows!$B$4:$B$519,$C12,Workflows!$D$4:$D$519,H$4) -> 0 | I12: =COUNTIFS(Workflows!$B$4:$B$519,$C12,Workflows!$D$4:$D$519,I$4) -> 0 | K12: =COUNTIFS('Dispatch flows'!$B$4:$B$74,$C12,'Dispatch flows'!$D$4:$D$74,K$4) -> 0 | L12: =COUNTIFS('Dispatch flows'!$B$4:$B$74,$C12,'Dispatch flows'!$D$4:$D$74,L$4) -> 0 | M12: =COUNTIFS('Dispatch flows'!$B$4:$B$74,$C12,'Dispatch flows'!$D$4:$D$74,M$4) -> 0 | N12: =COUNTIFS('Dispatch flows'!$B$4:$B$74,$C12,'Dispatch flows'!$D$4:$D$74,N$4) -> 0 | O12: =COUNTIFS('Dispatch flows'!$B$4:$B$74,$C12,'Dispatch flows'!$D$4:$D$74,O$4) -> 0 | AF12: 42956 | AG12: =COUNTIF(Workflows!$U$4:$U$4024,"<="&AF12) -> 8
C13: MetroPCS | D13: =COUNTIFS(Workflows!$B$4:$B$519,$C13,Workflows!$D$4:$D$519,D$4) -> 0 | E13: =COUNTIFS(Workflows!$B$4:$B$519,$C13,Workflows!$D$4:$D$519,E$4) -> 0 | F13: =COUNTIFS(Workflows!$B$4:$B$519,$C13,Workflows!$D$4:$D$519,F$4) -> 1 | G13: =COUNTIFS(Workflows!$B$4:$B$519,$C13,Workflows!$D$4:$D$519,G$4) -> 0 | H13: =COUNTIFS(Workflows!$B$4:$B$519,$C13,Workflows!$D$4:$D$519,H$4) -> 0 | I13: =COUNTIFS(Workflows!$B$4:$B$519,$C13,Workflows!$D$4:$D$519,I$4) -> 0 | K13: =COUNTIFS('Dispatch flows'!$B$4:$B$74,$C13,'Dispatch flows'!$D$4:$D$74,K$4) -> 0 | L13: =COUNTIFS('Dispatch flows'!$B$4:$B$74,$C13,'Dispatch flows'!$D$4:$D$74,L$4) -> 0 | M13: =COUNTIFS('Dispatch flows'!$B$4:$B$74,$C13,'Dispatch flows'!$D$4:$D$74,M$4) -> 0 | N13: =COUNTIFS('Dispatch flows'!$B$4:$B$74,$C13,'Dispatch flows'!$D$4:$D$74,N$4) -> 0 | O13: =COUNTIFS('Dispatch flows'!$B$4:$B$74,$C13,'Dispatch flows'!$D$4:$D$74,O$4) -> 0 | AF13: 42957 | AG13: =COUNTIF(Workflows!$U$4:$U$4024,"<="&AF13) -> 8
C14: Telkomsel | D14: =COUNTIFS(Workflows!$B$4:$B$519,$C14,Workflows!$D$4:$D$519,D$4) -> 0 | E14: =COUNTIFS(Workflows!$B$4:$B$519,$C14,Workflows!$D$4:$D$519,E$4) -> 0 | F14: =COUNTIFS(Workflows!$B$4:$B$519,$C14,Workflows!$D$4:$D$519,F$4) -> 0 | G14: =COUNTIFS(Workflows!$B$4:$B$519,$C14,Workflows!$D$4:$D$519,G$4) -> 4 | H14: =COUNTIFS(Workflows!$B$4:$B$519,$C14,Workflows!$D$4:$D$519,H$4) -> 0 | I14: =COUNTIFS(Workflows!$B$4:$B$519,$C14,Workflows!$D$4:$D$519,I$4) -> 0 | K14: =COUNTIFS('Dispatch flows'!$B$4:$B$74,$C14,'Dispatch flows'!$D$4:$D$74,K$4) -> 0 | L14: =COUNTIFS('Dispatch flows'!$B$4:$B$74,$C14,'Dispatch flows'!$D$4:$D$74,L$4) -> 0 | M14: =COUNTIFS('Dispatch flows'!$B$4:$B$74,$C14,'Dispatch flows'!$D$4:$D$74,M$4) -> 0 | N14: =COUNTIFS('Dispatch flows'!$B$4:$B$74,$C14,'Dispatch flows'!$D$4:$D$74,N$4) -> 0 | O14: =COUNTIFS('Dispatch flows'!$B$4:$B$74,$C14,'Dispatch flows'!$D$4:$D$74,O$4) -> 0 | AF14: 42958 | AG14: =COUNTIF(Workflows!$U$4:$U$4024,"<="&AF14) -> 8
AF15: 42959 | AG15: =COUNTIF(Workflows!$U$4:$U$4024,"<="&AF15) -> 8
AF16: 42960 | AG16: =COUNTIF(Workflows!$U$4:$U$4024,"<="&AF16) -> 8
AF17: 42961 | AG17: =COUNTIF(Workflows!$U$4:$U$4024,"<="&AF17) -> 8
AF18: 42962 | AG18: =COUNTIF(Workflows!$U$4:$U$4024,"<="&AF18) -> 8
AF19: 42963 | AG19: =COUNTIF(Workflows!$U$4:$U$4024,"<="&AF19) -> 8
AF20: 42964 | AG20: =COUNTIF(Workflows!$U$4:$U$4024,"<="&AF20) -> 8
AF21: 42965 | AG21: =COUNTIF(Workflows!$U$4:$U$4024,"<="&AF21) -> 8
AF22: 42966 | AG22: =COUNTIF(Workflows!$U$4:$U$4024,"<="&AF22) -> 8
AF23: 42967 | AG23: =COUNTIF(Workflows!$U$4:$U$4024,"<="&AF23) -> 8
AF24: 42968 | AG24: =COUNTIF(Workflows!$U$4:$U$4024,"<="&AF24) -> 8
AF25: 42969 | AG25: =COUNTIF(Workflows!$U$4:$U$4024,"<="&AF25) -> 8
AF26: 42970 | AG26: =COUNTIF(Workflows!$U$4:$U$4024,"<="&AF26) -> 8
... AF337: 43281 | AG337: =COUNTIF(Workflows!$U$4:$U$4024,"<="&AF337) -> 37

Sheet Workflows
B1: Link
B2: Account | D2: Flow | H2: Krrish Dev. | J2: Classification | L2: Threshold Config | N2: Parsing | W2: % in Training data | AA2: Recall on test set | AD2: Full Auto Error on test set
D3: Phase | E3: Name | F3: Krrish Name | G3: Type | J3: Status | K3: Model | N3: Entity | O3: Atom | P3: Configuration | Q3: Note | R3: Status | T3: Description | U3: Production Date | W3: Total | X3: External | Y3: Internal | AA3: TH = 0.5 | AB3: Lower TH | AD3: TH = 0.5 | AE3: Higher TH | AF3: MRFPR
B4: Globe | D4: Prod. - Activated | E4: Rated events extraction | F4: Rated Events Extraction | G4: Ext. | J4: Trained Desc - 0.5, Summ - 0.5 | K4: 1. N gram - 2 2. Chi2 - 20% 3. Random Forest - 100 trees | L4: 0.5, 0.3 | N4: MSISDN (M) | O4: Phone Number | P4: PhoneNumberExtractor(exclusion_list = ["requestor phone", "contact phone", "requestor contact","requestor's phone", "contact's phone", "requestor's contact"], first_digit = 9) | R4: configured | T4: User/s usage report (data/voice/SMS) | U4: 42953 | W4: 0.0491 | X4: 0.0516 | Y4: - | AA4: 0.85 | AB4: =161/189 -> 0.85185185 | AD4: 0.11 | AE4: 0.11 | AF4: 1-8 | AG4: =1/8 -> 0.125
N5: DATE_FROM, DATE_TO | O5: Date-Range | P5: DateRangeExtractor(from_range_name = 'DATE_FROM', to_range_name = 'DATE_TO', time_zone = 'Asia/Manila') | R5: configured
N6: VOICE | O6: Regex | P6: RegexExtractor(extraction_regex = r"""voice|call?s""" , indicator = True) | R6: configured
N7: SMS | O7: Regex | P7: RegexExtractor(extraction_regex = r"""sms|text|txt|msg|messag?e?s""" , indicator = True) | R7: configured
N8: DATA | O8: Regex | P8: RegexExtractor(extraction_regex = r"""data|internet""" , indicator = True) | R8: configured
N9: ROAMING_IND | O9: Regex | P9: RegexExtractor(extraction_regex = r"""\\sroaming|\\sroam\\s""" , indicator = True) | R9: configured
B10: Globe | D10: Prod. - Activated | E10: LTP no load received | F10: LTP_NO_LOAD_RECEIVE | G10: Ext. | L10: 0.7,0.15 | N10: MSISDN (M) | O10: Phone Number | P10: PhoneNumberExtractor(exclusion_list = ["requestor phone", "contact phone", "requestor contact"] ,first_digit = 9) | R10: configured | T10: LTP stands for Load Tipid Plan. A Hybrid prepaid-postpaid program. Training issue. RPL flow where subscriber did not received monthly recharge. This is a training issue due to CSR did not validate completely why subs did not receive load and upon checking. It is a valid scenario where subs is still in collection. | U10: 42953 | W10: 0.0259 | X10: 0.0272 | Y10: - | AA10: 0.88 | AB10: 0.88 | AD10: 0.05 | AE10: 0.05 | AF10: 1-9 | AG10: =1/9 -> 0.11111111
N11: SEEDING_DATE | O11: Regex | P11: RegexExtractor(extraction_regex = r"""((seed|sedd|seeed)(.{1,50})(\\b((?:[1-9]|0[1-9]|[1-2][0-9]|3[0-1]))(\\s|$)))|((\\b1st)|(21st)|(31st)|(\\b2nd)|(22nd)|(10th)|(11th)|(12th)|(13th)|(\\b3rd)|(23rd)|([1-2]?(0|[4-9])th))""" , integer_indicator = True, length_limit = 2, default_value = datetime.datetime.now().strftime('%d')) | R11: configured
B12: Globe | D12: Prod. - Activated | E12: ASMM variance found base | F12: MEDIATION_REPORT | G12: Ext. | L12: 0.5,0.5 | N12: FILE_IDENTIFIER (M) | O12: Globe_ASMM | P12: Globe_ASMMVariance_FileIdExtractor() | Q12: Comes in an attached .zip file | R12: configured | T12: ASMM Variance found base. Summary contains "Variance found base on ASMM VS TC base on daily analysis and A&C balance report“ | U12: 42953 | W12: 0.0092 | X12: 0.0097 | Y12: - | AA12: 1 | AB12: 1 | AD12: 0 | AE12: 0 | AF12: 0-0 | AG12: 0
B13: Globe | D13: Prod. - Activated | E13: Hold activity cancellation | F13: Hold Activity Cancellation | G13: Ext. | L13: 0.4,0.2 | N13: ORDER_ID | O13: Regex | P13: RegexExtractor(extraction_regex = r"""(\\D\\d{9}\\d?)([a]|[A])""", integer_indicator = True) | R13: configured | T13: Order cancellation in Hold activity. Script is being used to enable cancel order button | U13: 42953 | W13: 0.0076 | X13: 0.008 | Y13: - | AA13: 0.4 | AB13: 0.84705882 | AD13: 0.03 | AE13: 0.03 | AF13: 5-32 | AG13: =5/32 -> 0.15625
N14: MSISDN | O14: Phone Number | P14: PhoneNumberExtractor(exclusion_list = ["requestor phone", "contact phone", "requestor contact","requestor's phone", "contact's phone", "requestor's contact"], first_digit = 9) | R14: configured
B15: Globe | D15: Prod. - Activated | E15: Duo Alignment | F15: Duo Alignment | G15: Ext. | L15: 0.5,0.25 | N15: Multiple | O15: Globe_Duoalignment | P15: Default Values | R15: configured | U15: 43089 | W15: 0.0165 | X15: 0.0173 | Y15: - | AF15: 0-1 | AG15: 0
B16: Globe | D16: Prod. - Activated | E16: Reconnection Checking | F16: Reconnection | G16: Ext. | L16: 0.7, 0.25 | N16: MSISDN | O16: Phone Number | P16: PhoneNumberExtractor(exclusion_list = ["requestor phone", "contact phone", "requestor contact","requestor's phone", "contact's phone", "requestor's contact"], first_digit = 9) | R16: configured | U16: 42988 | W16: 0.0132 | X16: 0.0138 | Y16: - | AF16: 11-25 | AG16: =11/25 -> 0.44
N17: TICKET_DATE | O17: Create Date | P17: CreateDateExtractor(timezone_offset = 13)
B18: Globe | D18: Prod. - Activated | E18: Bulk Barring | F18: Bulk Barring | G18: Ext. | L18: 0.5,0.4 | N18: DATA, File | O18: Globe_Bulkbarring | P18: GlobeBulkbarringExtractor() | Q18: May come in an attached .zip file | R18: configured | U18: 43089
B19: Globe | D19: Dev. | E19: Misaligned Component - MRF | G19: Ext. | N19: MSISDN
N20: Cycle_Month | Q20: if date range - last date
N21: Cycle_Year | Q21: usually prefaced by "Occurrence Date"
B22: Globe | D22: Dev. - Testing | E22: SRM Extraction | F22: SRM Extraction | G22: Ext. | L22: 0.5,0.3 | N22: Multiple | O22: GlobeSrmExtractionExtractor | P22: GlobeSrmExtractionExtractor() | R22: configured
N23: Request_Type | O23: Regex | P23: RegexExtractor("entity_name"= "Request_Type", "extraction_regex"= "(?<=Request\\sType(?!\\n)).*", "remove_char"=":", "replace_char"= ["^\\s",""]) | R23: configured
N24: Resource_Type | O24: Regex | P24: RegexExtractor("entity_name"= "Resource_Type", "extraction_regex"= "(?<=Resource\\sType(?!\\n)).*", "remove_char"=":", "replace_char"= ["^\\s",""]) | R24: configured
N25: Resource | O25: Regex | P25: RegexExtractor("entity_name"= "Resource", "extraction_regex"= "(?<=Resource)(:?)(\\s?)\\d.*", "remove_char"=":", "replace_char"= ["^\\s",""]) | R25: configured
N26: Status | O26: Regex | P26: RegexExtractor("entity_name"= "Status", "extraction_regex"= "(?<=Status(?!\\n)).*", "remove_char"=":", "replace_char"= ["^\\s",""]) | R26: configured
N27: Category | O27: Regex | P27: RegexExtractor("entity_name"= "Category", "extraction_regex"= "(?<=Category(?!\\n)).*", "remove_char"=":", "replace_char"= ["^\\s",""]) | R27: configured
N28: Area_Name | O28: Regex | P28: RegexExtractor("entity_name"= "Area_Name", "extraction_regex"= "(?<=Area\\sName(?!\\n)).*", "remove_char"=":", "replace_char"= ["^\\s",""]) | R28: configured
N29: Post_Pre | O29: Regex | P29: RegexExtractor("entity_name"= "Post_Pre", "extraction_regex"= "(?<=Post\\s\/\\sPre(?!\\n)).*", "remove_char"=":", "replace_char"= ["^\\s",""]) | R29: configured
N30: Date_From | O30: Regex | P30: RegexExtractor("entity_name"= "Date_From", "extraction_regex"= "(?<=Date\\sFrom(?!\\n)).*", "remove_char"=":", "replace_char"= ["^\\s",""]) | R30: configured
N31: Date_To | O31: Regex | P31: RegexExtractor("entity_name"= "Date_To", "extraction_regex"= "(?<=Date\\sTo(?!\\n)).*", "remove_char"=":", "replace_char"= ["^\\s",""]) | R31: configured
B33: Sprint | D33: Prod. - Activated | E33: Complete order | F33: complete order | G33: Ext. | J33: Trained Desc - 0.5, Summ - 0.5 | K33: 1. N gram - 2 2. Chi2 - 20% 3. Random Forest - 100 trees | L33: 0.8,0.5 | N33: Order_Number (M) | O33: Regex | P33: RegexExtractor(extraction_regex =r"""((COM\\d)|(DM\\d{2}))-?O-?\\d{6}\\d?\\d?""", remove_char = "-", upper_case = True) | R33: configured | T33: Completing orders that have gotten stuck in an incomplete status | U33: 42953 | W33: 0.0203 | X33: 0.0407 | Y33: - | AA33: 0.92 | AB33: 0.92 | AD33: 0.09 | AE33: 0.04 | AF33: 10-37 | AG33: =10/37 -> 0.27027027
B34: Sprint | D34: Prod. - Activated | E34: MPD date incorrect | F34: Sprint_INCORRECT MPD DATE CORRECTED | G34: Ext. | L34: 0.7,0.5 | N34: BAN (M) | O34: Regex | P34: RegexExtractor(extraction_regex =r"""(^|\\D)\d{9}(\\b|\\D)""",exclusion_list = ["Secondary", "secondary"],exclusion_offset=30, unique_indicator = False, integer_indicator = True) | Q34: May appear in the Summary field, Take only Primary number | R34: configured | T34: Resetting monthly payment dates on suspended prepaid accounts | U34: 42953 | W34: 0.0037 | X34: 0.0074 | Y34: - | AA34: 0.67 | AB34: 0.67 | AD34: 0.12 | AE34: 0.02 | AF34: 6-17 | AG34: =6/17 -> 0.35294118
B35: Sprint | D35: Prod. - Activated | E35: Re-push Order | F35: Repush Order Line | G35: Ext. | L35: 0.5 0.5 | N35: Order_Number (M) | O35: Sprint_Repush | R35: configured | U35: 42988 | W35: 0.0086 | X35: 0.0173 | Y35: - | AA35: 1 | AB35: 1 | AD35: 0 | AE35: 0 | AF35: 0-0 | AG35: 0
B36: Sprint | D36: Prod. - Activated | E36: Edit Memo | F36: Sprint_Mask Memo | G36: Ext. | L36: 0.6,0.2 | N36: BAN | O36: Regex | P36: RegexExtractor(extraction_regex =r"""(^|\\D)\d{9}(\\b|\\D)""", inclusion_list=["BAN","BAN:"], inclusion_offset = 20, unique_indicator = False, integer_indicator = True) | R36: configured | U36: 42988 | W36: 0.0115 | X36: 0.0231 | Y36: - | AA36: 0.92 | AB36: 1 | AD36: 0.06 | AE36: 0.04 | AF36: 2-11 | AG36: =2/11 -> 0.18181818
N37: PTN | O37: Phone Number | P37: PhoneNumberExtractor(exclusion_list = ["requestor phone", "contact phone", "requestor contact","Office Phone","Mobile Phone","Number"]) | R37: configured
N38: Memo_ID | O38: Regex | P38: RegexExtractor(extraction_regex =r"""(^|\\D)I?\\d?\\d{10}(\\b|\\D)""",inclusion_list = ["Memo ID"], inclusion_offset = 20, remove_char = " ", upper_case = True) | R38: configured
N39: Memo_Details_to_Remove | O39: Regex | P39: RegexExtractor(extraction_regex =r"""Memo\\s{,3}Details\\s{,3}to\\s{,3}Remove:(.+)\\n""",remove_char = "(m|M)emo\\s{,3}(d|D)etails\\s{,3}(T|t)o\\s{,3}(r|R)emove:") | R39: configured
B40: Sprint | D40: Prod. - Activated | E40: Clear PI PTN | F40: Sprint Clear PI PTN | G40: Ext. | L40: 0.4,0.1 | N40: PTN | O40: Phone Number | P40: PhoneNumberExtractor(exclusion_list = ["requestor phone", "contact phone", "requestor contact","Office Phone","Mobile Phone","Number"]) | R40: configured | U40: 43067
B41: Sprint | D41: Prod. - Activated | E41: Cancel Order | F41: Sprint Cancel Order | G41: Ext. | L41: 0.6, 0.3 | N41: Order_Number (M) | O41: Regex | P41: RegexExtractor(extraction_regex =r"""((COM\\d)|(DM\\d{2}))-?O-?\\d{6}\\d?\\d?""", remove_char = "-", upper_case = True) | R41: configured | U41: 43053
B42: Sprint | D42: Prod. - Activated | E42: CSM-RPL Production Sanity | F42: CSM-RPL Production Sanity | G42: Int. | J42: Trained Desc - 0.1, Summ - 0.9 | L42: 0.5,0.5 | N42: PTN (M) | O42: Phone Number | P42: PhoneNumberExtractor("icnlusion_list" = ["PTN"], inclusion_offset = 30) | Q42: MSISDN | R42: configured | U42: 42953 | W42: Non-UTS, Received by e-mail | AA42: 1 | AB42: 1 | AD42: 0 | AE42: 0 | AF42: 0-0 | AG42: 0
B43: Sprint | D43: Prod. - Activated | E43: Threshold_Break | F43: Advance MRC Threshold Break | G43: Int. | L43: 0.9,0.5 | N43: TZ (M) | O43: Regex | P43: RegexExtractor(extraction_regex =r"""(TZ|Time Zone)(\\s{,5}?)([\\d]+)""", remove_char = "[^0-9]") | R43: configured | U43: 42953 | W43: 0.0025 | X43: - | Y43: 0.0049 | AA43: 1 | AB43: 1 | AD43: 0 | AE43: 0 | AF43: 0-0 | AG43: 0
B44: Sprint | D44: Prod. - Activated | E44: First RC | F44: SPRINT Prepaid First RC | G44: Int. | L44: 0.5,0.3 | N44: BAN_SUBSCRIBER | O44: Regex | R44: configured | U44: 42988 | W44: Non-UTS, Received by e-mail | AA44: 1 | AB44: 1 | AD44: 0 | AE44: 0 | AF44: 0-0 | AG44: 0
B45: Sprint | D45: Prod. - Activated | E45: Zero RC | F45: SPRINT Prepaid Zero RC | G45: Int. | L45: 0.5,0.3 | N45: BAN_SUBSCRIBER | O45: Regex | R45: configured | U45: 43053
B46: Sprint | D46: Prod. - Activated | E46: Linkage Wrapper | F46: SPRINT Linkage Wrapper | G46: Int. | L46: 0.6, 0.5 | N46: TZ (M) | O46: Regex | P46: RegexExtractor(extraction_regex =r"""(TZ|Time Zone)(\\s{,5}?)([\\d]+)""", remove_char = "[^0-9]") | R46: configured | U46: 43067
B48: XL Axiata | D48: Prod. - Activated | E48: Age Out | F48: Age_Out | G48: Ext. | J48: Trained Desc - 0.4, Summ - 0.6 | K48: 1. N gram - 2 2. Chi2 - 20% 3. Random Forest - 100 trees | L48: 0.7,0.3 | N48: MSISDN (M) | O48: Xlcom_Msisdn | P48: XlcomMsisdnExtractor(entity_name:="MSISDN", inclusion_list= ["Description:"],inclusion_offset= 4000) | R48: configured | T48: Customer/frontline activate subscriber, then they request to Billing Helpdesk - change status from Aging to Assigned | U48: 42988 | W48: 0.1175 | X48: 0.12409439 | Y48: - | AA48: 1 | AB48: 1 | AD48: 0.03 | AF48: 1-5 | AG48: =1/5 -> 0.2
B49: XL Axiata | D49: Prod. - Activated | E49: Customer Booking | F49: Customer_Booking | G49: Ext. | L49: 0.6,0.4 | N49: MSISDN (M) | O49: Xlcom_Msisdn | P49: XlcomMsisdnExtractor(entity_name:="MSISDN", inclusion_list= ["Description:"],inclusion_offset= 4000) | R49: configured | T49: Customer/frontline activate subscriber, then they request to Billing Helpdesk - change status from Reserved Prio to Reserved VRM | U49: 42988 | W49: 0.0095 | X49: 0.010065476 | Y49: - | AA49: 0.95 | AB49: 0.95 | AD49: 0.1 | AF49: 0-0 | AG49: 0
B50: XL Axiata | D50: Prod. - Activated | E50: Unsync VRM Active/Cancel | F50: Unsync CM CRM | G50: Ext. | L50: 0.5,0.2 | N50: MSISDN (M) | O50: Xlcom_Msisdn | P50: XlcomMsisdnExtractor(entity_name:="MSISDN", inclusion_list= ["Description:"],inclusion_offset= 4000) | R50: configured | T50: Customer/frontline want to checking subscriber in CRM Smartclient but it’s was not sync in status (Cancel/Active) with CM DB/VRM Tool | U50: 42988 | W50: Non-UTS, Received by e-mail | AA50: =19/24 -> 0.79166667 | AB50: =21/24 -> 0.875 | AD50: 0 | AE50: 0 | AF50: 2-10
B51: XL Axiata | D51: Dev. - Testing | E51: Wrong Charging | F51: Wrong Charging | G51: Ext. | L51: 0.8,0.5 | N51: MSISDN (M) | O51: Xlcom_Msisdn | P51: XlcomMsisdnExtractor(entity_name:="MSISDN", inclusion_list= ["Description:"],inclusion_offset= 4000) | R51: configured | T51: Customer/frontline complaint if subscriber got wrong charge based on call detail at specific time frame when compared with benefit from Active Price Plan / AO Offer. | W51: 0.1662 | X51: 0.1756 | Y51: - | AA51: 0.96 | AB51: 0.96 | AD51: =9/269 -> 0.033457249 | AF51: 11-121 | AG51: =11/121 -> 0.090909091
B52: XL Axiata | D52: Prod. - Deactivated | E52: Quota not update | F52: Quota NUD | G52: Ext. | L52: 0.7,0.5 | N52: MSISDN (M) | O52: Xlcom_Msisdn | P52: XlcomMsisdnExtractor(entity_name:="MSISDN", inclusion_list= ["Description:"],inclusion_offset= 4000) | R52: configured | T52: Customer/frontline complaint if subscriber can’t check quota based on benefit of Active AO Offer from UMB/Network *123# | W52: 0.2447 | X52: 0.25850647 | Y52: - | AA52: 1 | AB52: 1 | AD52: 0.03 | AE52: =3/549 -> 0.0054644809 | AF52: 9-67 | AG52: =9/67 -> 0.13432836
N53: ISSUE_DATE | O53: DateTimeExtractor | P53: DateTimeExtractor(entity_name= "ISSUE_DATE", inclusion_list: =["cust sudah rec","aktivasi","activation date","waktu","tf","time frame","Time Frame","Time frame","tanggal","t.frime","kejadian"], inclusion_offset:=40, format_to_extract= 2, unique_indicator = false) | R53: configured | U53: 43125
N54: SOCCD | O54: XlcomSocDictExtractor | P54: XlcomSocDictExtractor(entity_name="SOCCD") | R54: configured
B55: XL Axiata | D55: Labeling | E55: Recurring Failed
B56: XL Axiata | D56: Prod. - Activated | E56: OC Insufficient Balance | F56: OC Insufficient Balance | G56: Ext. | L56: 0.5,0.4 | N56: MSISDN (M) | O56: Xlcom_Msisdn | P56: XlcomMsisdnExtractor(entity_name:="MSISDN", inclusion_list= ["Description:"],inclusion_offset= 4000, exclusion_list=["VLR address"]) | R56: configured | U56: 43061 | W56: 0.0411 | X56: 0.0434 | Y56: -
B58: Cricket | D58: Prod. - Activated | E58: Auto Pay Issue | F58: Un-enroll AutoPay | G58: Ext. | J58: Trained Desc - 0.5, Summ - 0.5 | K58: 1. N gram - 2 2. Chi2 - 20% 3. Random Forest - 250 trees | L58: 0.5,0.2 | N58: BAN (M) | O58: Regex | P58: RegexExtractor(extraction_regex =r"""(^|\\D)\d{9}(\\b|\\D)""", unique_indicator = True, integer_indicator = True) | R58: configured | U58: 42988 | W58: 0.0215 | X58: 0.0423 | Y58: - | AA58: =52/68 -> 0.76470588 | AB58: =67/68 -> 0.98529412 | AD58: 0.08 | AE58: 0.08 | AF58: 8-12 | AG58: =8/12 -> 0.66666667
B59: Cricket | D59: Prod. - Activated | E59: Cricket Cancel Port In Eligibility Check | F59: Cricket Cancel Port In Eligibility Check | G59: Ext. | L59: 0.5,0.2 | N59: CTN | O59: CricketEligibilityCheck | R59: configured | U59: 43158 | W59: 0.029073286 | X59: 0.0572 | Y59: -
B60: Cricket | D60: Descoped | E60: Cancel Port | F60: Cancel Port In/Out | G60: Ext. | L60: 0.65,0.5 | N60: PTN | O60: Phone Number | P60: PhoneNumberExtractor() | R60: configured | W60: 0.1848 | X60: 0.3638 | Y60: - | AA60: =533/550 -> 0.96909091 | AB60: =533/550 -> 0.96909091 | AD60: 0.03442029 | AE60: =10/522 -> 0.019157088
N61: BAN | O61: Regex | P61: RegexExtractor(extraction_regex =r"""(^|\\D)\d{9}(\\b|\\D)""", unique_indicator = True, integer_indicator = True) | R61: configured
B62: Cricket | D62: Descoped | E62: Complete Port | F62: Complete Port In/Out | G62: Ext. | L62: 0.5,0.2 | N62: PTN | O62: Phone Number | P62: PhoneNumberExtractor() | R62: configured | U62: 42988 | W62: 0.0183 | X62: 0.036 | Y62: - | AA62: =10/51 -> 0.19607843 | AB62: =34/51 -> 0.66666667 | AD62: =2/12 -> 0.16666667 | AE62: =2/12 -> 0.16666667 | AF62: 33-59 | AG62: =33/59 -> 0.55932203
B63: Cricket | D63: Descoped | E63: Change CTN | G63: Ext. | N63: CTN | W63: 0.0136 | X63: 0.0269 | Y63: -
B64: Cricket | D64: Descoped | E64: Complete Order | G64: Ext. | N64: Order ID | O64: Regex | P64: RegexExtractor(extraction_regex =r"""(ORD)-?O-?\\d{6}\\d?\\d?""", remove_char = "-", upper_case = True) | R64: configured | W64: 0.0056 | X64: 0.0109 | Y64: -
N65: PTN | O65: Phone Number | P65: PhoneNumberExtractor() | R65: configured
N66: BAN | O66: Regex | P66: RegexExtractor(extraction_regex =r"""(^|\\D)\d{9}(\\b|\\D)""", unique_indicator = True, integer_indicator = True) | R66: configured
B67: Cricket | D67: Descoped | E67: Resume Subscriber | G67: Ext. | N67: PTN | W67: 0.0075 | X67: 0.0147 | Y67: -
N68: BAN
B69: Cricket | D69: Descoped | E69: Unable access data | G69: Ext. | W69: 0.0117 | X69: 0.0231 | Y69: -
B70: Cricket | D70: Prod. - Activated | E70: BLDECMPRECON Issue | F70: BLDECMPRECON | G70: Int. | J70: Trained Desc - 0.4, Summ - 0.6 | K70: 1. N gram - 2 2. Chi2 - 20% 3. Random Forest - 100 trees | L70: 0.4,0.3 | N70: - | R70: configured | U70: 42988 | W70: 0.0115 | X70: - | Y70: 0.0234 | AA70: 0.97 | AB70: 1 | AD70: 0 | AE70: 0 | AF70: 0-0 | AG70: 0
B71: Cricket | D71: Prod. - Activated | E71: Rejects in Confirmation | F71: Rejects in Confirmation | G71: Int. | L71: 0.5, 0.15 | N71: - | R71: configured | U71: 43123 | W71: 0.0020641026 | X71: - | Y71: 0.0042
B72: Cricket | D72: Prod. - Activated | E72: Portal Orders Payment Statistics for Last Hour | F72: Portal Orders Payment Statistics for Last Hour | G72: Int. | L72: 0.6, 0.3 | N72: - | R72: configured | U72: 43138
B73: Cricket | D73: Prod. - Activated | E73: CSM Pending Payments From CSPYMREPRCSS | F73: CSM Pending Payments From CSPYMREPRCSS | G73: Int. | L73: 0.5, 0.4 | N73: - | R73: configured | U73: 43158
B74: Cricket | D74: Dev. - Testing | E74: Rejects in Billing | F74: Rejects in billing | G74: Int. | L74: 0.5, 0.4 | N74: -
B75: Cricket | D75: Prod. - Activated | E75: BLDECOMSUBTX | F75: BLDECOMSUBTX | G75: Int. | L75: 0.25, 0.2 | N75: - | U75: 43158
B77: USCC | D77: Prod. - Activated | E77: Cancel FA | F77: Cancel FA | G77: Ext. | J77: Trained Desc - 0.5, Summ - 0.5 | K77: 1. N gram - 2 2. Chi2 - 20% 3. Random Forest - 100 trees | L77: 0.6,0.35 | N77: Customer ID | O77: Regex | P77: RegexExtractor(entity_name="Customer ID", "inclusion_list"= ["Customer id"],"inclusion_offset":=20, "exclusion_list": = ["\\bFA\\b","FA_ID","FA ID","Cancel FA","cancel the following FA","please close FA","FA Cancel"], "exclusion_offset"=20, "extraction_regex"= (^|\\D)\\d{9}(\\b|\\D), "unique_indicator": = True, "integer_indicator": = True) | R77: configured | U77: 43062 | W77: 0.1575
N78: FA_ID | O78: Regex | P78: RegexExtractor("entity_name"="\\bFA\\b", "FA_ID", "inclusion_list": = ["FA_ID","FA ID","Cancel FA","cancel the following FA","please close FA","FA Cancel"], "inclusion_offset"=80, "exclusion_list"= ["Customer id"],"exclusion_offset":=20, "extraction_regex"= "(^|\\D)\\d{9}(\\b|\\D)", "integer_indicator"= True) | R78: configured
B79: USCC | D79: Prod. - Activated | E79: Prepaid Customer | F79: PREPAID CUSTOMER WITHOUT SERVICE | G79: Ext. | L79: 0.6,0.3 | N79: Customer_ID | O79: Regex | P79: RegexExtractor(entity_name="Customer ID", "inclusion_list"= ["Customer id"],"inclusion_offset":=20, "extraction_regex"= (^|\\D)\\d{9}(\\b|\\D), "unique_indicator": = True, "integer_indicator": = True) | R79: configured | U79: 43433 | W79: 0.0574
N80: MDN | O80: Phone Number | P80: PhoneNumberExtractor(inclusion_list = ["MDN"]) | R80: configured
B81: USCC | D81: Prod. - Activated | E81: Registration Issue | F81: Prepaid Registration | G81: Ext. | L81: 0.5,0.2 | N81: Customer ID | O81: Regex | P81: RegexExtractor(entity_name="Customer ID", "inclusion_list"= ["Customer id"],"inclusion_offset":=20, "extraction_regex"= (^|\\D)\\d{9}(\\b|\\D), "unique_indicator": = True, "integer_indicator": = True) | R81: configured | U81: 43072 | W81: 0.0347
N82: Attachment | O82: UsccPrepaidRegistrationExtractor | P82: UsccPrepaidRegistrationExtractor(entit_name="Attachment")
B83: USCC | D83: Dev. - Testing | E83: ESN Blacklist | F83: USCC ESN | G83: Ext. | L83: 0.55,0.2 | N83: ESN_MEID | O83: Regex | P83: RegexExtractor(entity_name="ESN/MEID", "inclusion_list"= ["esn","meid","esn/meid"],"inclusion_offset":=20, "extraction_regex"= (^|\\D)\\d?\\d{17}(\\b|\\D), "integer_indicator": = True) | R83: configured | W83: 0.0102
B84: USCC | D84: Dev. - Testing | E84: Billing Rejects | F84: Billing Rejects | G84: Both | L84: 0.8,0.3 | N84: Defect ID | O84: Regex | P84: 1. RegexExtractor(entity_name="Defect ID", "inclusion_list"= ["BILLING_CYCLE","BILL_CYCLE","defect","hold"],"inclusion_offset":=100, "extraction_regex"= \\D\\d?\\d?\\d{5}(\\D|$), "integer_indicator": = True) 2. RegexExtractor(entity_name="Defect ID", "extraction_regex"= (D(\\#?))\\d?\\d?\\d{5}(\\D|$), "integer_indicator": = True) | R84: configured | W84: 0.0421
B85: USCC | D85: Prod. - Activated | E85: PULL BILLS AFP | F85: PULL BILLS AFP | G85: Ext. | L85: 0.5, 0.4 | N85: AFP_NAME | O85: Regex | P85: RegexExtractor(entity_name="AFP_NAME", "extraction_regex"= "DD.USC.\\d{4}.\\d{2}.\\d{4}.\\*.afp") | U85: 43167
B86: USCC | D86: Dev. | E86: Overage Notification | F86: Overage Notification | G86: Ext. | L86: 0.6,0.1
B87: USCC | D87: Dev. | E87: RC Drop | F87: RC Drop | G87: Int. | L87: 0.5, 0.4
B89: Bell Canada | D89: Dev. | E89: ADD User | G89: Ext. | J89: Default | K89: Default | W89: 0.366 | X89: 0.625 | Y89: -
B90: Bell Canada | D90: Dev. | E90: DELETE User | G90: Ext. | W90: 0.366 | X90: 0.625 | Y90: -
B91: Bell Canada | D91: Dev. | E91: UPDATE User | G91: Ext. | W91: 0.366 | X91: 0.625 | Y91: -
B93: Airtel | D93: Prod. - Activated | E93: Order Not Generated | F93: Order Not Generated | G93: Ext. | J93: Trained Desc - 0.5, Summ - 0.5 | K93: 1. N gram - 2 2. Chi2 - 20% 3. Random Forest - 100 trees | L93: 0.6, 0.3 | N93: Mobile_Number | O93: Regex | P93: RegexExtractor: "entity_name": "Mobile_No", "extraction_regex":"((?<=\\D)|(?<=\\b)|(?<=''))[7-9](\\d{9})((?=\\b)|(?=\\s)|(?=\\D))", "integer_indicator": true,"replace_char": ["_"," _ "], "exclusion_list": ["sfo"], "exclusion_offset": 20 | Q93: No impact of full automation that is FP | U93: 43115 | W93: 0.366 | X93: 0.625 | Y93: -
N94: Mobile_Number | P94: AirtelPendingForActivationExtractor("entity_name" = ["Mobile_No"])
B95: Airtel | D95: Prod. - Activated | E95: SR and Task Closure | F95: SR and Task closure | G95: Ext. | L95: 0.8,0.5 | N95: SR Number | O95: Regex | P95: RegexExtractor( "entity_name"= "SR Number", "extraction_regex"="(?<=\D)\d{8}(?=(\D|$))") | Q95: No impact of full automation that is FP | U95: 43095
N96: LOB | O96: Regex | P96: ListExtractor( "entity_name"="LOB", "extraction_regex"= (\\bABGB\\b)|(\\bDTH\\b)|(\\bMobility\\b)|(\\bTelemedia\\b)|(\\bIT\\b), "inclusion_list"=["LOB"], "default_value"=['telemedia'])
B97: Airtel | D97: Prod. - Activated | E97: Pending for Activation | F97: Pending for Activation | G97: Ext. | L97: 0.6,0.3 | N97: Mobile_No | O97: Regex | P97: RegexExtractor: "entity_name": "Mobile_No", "extraction_regex":"((?<=\\D)|(?<=\\b)|(?<=''))[7-9](\\d{9})((?=\\b)|(?=\\s)|(?=\\D))", "integer_indicator": true, "exclusion_list": ["sfo"], "exclusion_offset": 20 | Q97: No impact of full automation that is FP | U97: 43096
N98: Mobile_No | O98: PendingForActivationExtractor | P98: AirtelPendingForActivationExtractor("entity_name" = ["Mobile_No"])
B99: Airtel | D99: Prod. - Activated | E99: NMS Release Scenario | F99: NMS Release Scenario | G99: Ext. | L99: 0.5, 0.2 | N99: From_Number_To_Number | O99: From_Number_To_Number | Q99: Impact on full automation
B100: Airtel | D100: Dev. - Testing | E100: P2P Request Deletion | F100: P2P Request Deletion | G100: Ext. | L100: 0.5, 0.3 | N100: Mobile_No | O100: Regex | P100: RegexExtractor("entity_name": "Mobile_No", "extraction_regex":"((?<=\\D)|(?<=\\b)|(?<=''))[7-9](\\d{9})((?=\\b)|(?=\\s)|(?=\\D))", "integer_indicator": true, "exclusion_list": ["regards"], "exclusion_offset": 500)
N101: Request_ID | O101: Regex | P101: RegexExtractor("entity_name": "Request_ID", "extraction_regex":"((?<=\\D)|(?<=\\b)|(?<=''))(\\d{7})((?=\\b)|(?=\\s)|(?=\\D))", "integer_indicator": true)
B102: Airtel | D102: Dev. | E102: P2P ID Creation | F102: P2P ID Creation | G102: Ext. | L102: 0.5, 0.3 | N102: Multiple | O102: airtel_p2p_id_creation_extractor
B103: Airtel | D103: Dev. | E103: Barring | F103: Barring | G103: Ext. | L103: 0.5, 0.2
B104: Airtel | D104: Prod. - Activated | E104: Unbarring | F104: Unbarring | G104: Ext. | L104: 0.7, 0.3 | N104: Mobile_Number | O104: Regex | Q104: Impact on full automation
B105: Airtel | D105: Dev. | E105: Task Closure | G105: Ext. | N105: Mobile_Number
B107: Tef Argentina | D107: Dev. | E107: Stuck Order | N107: Order_number
...

Sheet Dispatch flows
B2: Account | D2: Flow | H2: Krrish Dev. | J2: Classification | L2: Threshold Config | R2: % in Training data | V2: Recall on test set | Y2: Full Auto Error on test set
D3: Phase | E3: Support Group | F3: Support Group ID | G3: Flow Name | J3: Status | K3: Model | O3: Description | P3: Production Date | R3: Total | S3: External | T3: Internal | V3: TH = 0.5 | W3: Lower TH | Y3: TH = 0.5 | Z3: Higher TH
B4: Globe | D4: Prod. - Activated | E4: NBU | F4: SGP000000001133 | G4: Business | J4: Trained Desc - 0.5, Summ - 0.5 | K4: 1. N gram - 2 2. Chi2 - 20% 3. Random Forest - 200 trees | L4: 0.5 | P4: 42988
B5: Globe | D5: Prod. - Activated | E5: EPC | F5: SGP000000001130 | G5: Service Configuration | L5: 0.3 | P5: 42988
B6: Globe | D6: Descoped | E6: Usage | F6: SGP000000001367 | G6: PER Downstream Variance | L6: 0.3 | P6: 42988
B7: Globe | D7: Descoped | G7: Trending files with zero records | L7: 0.3
B8: Globe | D8: Descoped | G8: Variance found on CDR | L8: 0.3
B9: Globe | D9: Prod. - Activated | G9: Rejects | L9: 0.3 | P9: 43084
B11: USCC | D11: Descoped | G11: Amdocs SEVA | J11: Trained Desc - 0.5, Summ - 0.5 | K11: 1. N gram - 2 2. Chi2 - 20% 3. Random Forest - 200 trees | L11: 0.5
B12: USCC | D12: Prod. - Activated | G12: Recycle Event issue | L12: 0.6 | P12: 43116
B13: USCC | D13: Descoped | G13: Accelerate Device Financing | L13: 0.3
B14: USCC | D14: Descoped | G14: EOM | L14: 0.5
B15: USCC | D15: Prod. - Activated | G15: AR1JRNLEXT Running Long | L15: 0.4 | P15: 43116
B17: Sprint | D17: Prod. - Activated | G17: Sprint_API | J17: Trained Desc - 0.5, Summ - 0.5 | K17: 1. N gram - 2 2. Chi2 - 20% 3. Random Forest - 200 trees | L17: 0.5 | P17: 43167
B18: Sprint | D18: Prod. - Activated | G18: Sprint_DRF | L18: 0.5 | P18: 43167
B19: Sprint | D19: Prod. - Activated | G19: Sprint_MonAdjust | L19: 0.5 | P19: 43167

Sheet Amily PoC Status
B2: Globe | L2: Clustering
B4: Flow | D4: Classification | H4: Parsing | L4: Account | M4: Internal/External | N4: Supervised Evaluation | O4: Status
D5: IBM | E5: SAS | F5: FOSS | H5: IBM | I5: SAS | J5: FOSS | L5: Globe | M5: External | N5: Yes
B6: ASMM Variance found base | L6: Sprint | M6: Internal | N6: No
B7: Hold Activity Cancellation | I7: Evaluate | J7: Code | L7: TKS | M7: External | N7: No
B8: LTP No Load Receive | F8: ` | L8: TKS | M8: External | N8: Yes - Globe
B9: Misaligned Component - MRF | L9: TKS | M9: External | N9: Yes - Sprint
B10: PER Downstream Variance | L10: Metro | M10: External | N10: Yes - Globe
B11: Rated Events Extraction | I11: Evaluate | L11: Metro | M11: External | N11: Yes - Sprint
B12: Service Configuration | L12: XL Axiata | M12: External | N12: No
B13: Trending files with zero records
B14: Variance found on CDR
B15: Other | L15: Deployment feasibility PoC - all 3 tools
L16: Robust deployment feasibility PoC - with or w/o source code on
L17: OCR in python
B18: Sprint | L18: Gitlab
B20: Flow | D20: Classification | H20: Parsing
D21: IBM | E21: SAS | F21: FOSS | H21: IBM | I21: SAS | J21: FOSS
B22: Cancel Subscriber
B23: Complete Order | I23: Evaluate
B24: Daily DRF | I24: Evaluate | J24: Code
B25: Funds Not Sweeping
B26: MPD date incorrect
B27: Update PTN | I27: Evaluate | J27: Code
B28: Other

Sheet Amily PoC Contacts
C2: Vendor | E2: Name | G2: Phone Number | I2: E-mail
C3: IBM | E3: Jorge Vulej | G3: 050-9926431 | I3: ITZHAKVULEJ@IBM.COM
C4: IBM | E4: Omer Mizrachi | G4: 058-6485787 | I4: OMERMI@il.ibm.com
C5: SAS | E5: Yoni Barak | G5: 054-6400073 | I5: Jonathanb@miac.com
C6: SAS | E6: Hagay Goldman | G6: 052-6678805 | I6: Hagay.Goldman@sas.com
C7: SAS | E7: Dina Gelfond | G7: 052-8195582 | I7: DinaG@miac.com
C8: FOSS | E8: Yuval Feinstein | G8: 058-5113545 | I8: fyuval@gmail.com
